wheeltools/__init__.py
wheeltools/_version.py
wheeltools/tmpdirs.py
wheeltools/tools.py
wheeltools/wheeltools.py
wheeltools-0.1.0b1.dist-info/LICENSE
wheeltools-0.1.0b1.dist-info/METADATA
wheeltools-0.1.0b1.dist-info/WHEEL
wheeltools-0.1.0b1.dist-info/top_level.txt
wheeltools-0.1.0b1.dist-info/RECORD
